vedirect.py
vedirect-1.1.0.dist-info/METADATA
vedirect-1.1.0.dist-info/WHEEL
vedirect-1.1.0.dist-info/top_level.txt
vedirect-1.1.0.dist-info/RECORD
