Metadata-Version: 2.1
Name: vedirect
Version: 1.1.0
Summary: Interfaces with Victron VE.Direct devices
Home-page: http://github.com/Frankkkkk/python-vedirect
Author: Frank Villaro-Dixon
Author-email: frank@villaro-dixon.eu
License: MIT
Keywords: victron vedirect ve.direct ve direct mppt
Classifier: Development Status :: 3 - Alpha
Classifier: Topic :: Utilities
Classifier: License :: OSI Approved :: MIT License
Requires-Dist: pyserial
